[
  {
    "url": "https://www.servicii-funerare-timisoara.ro/",
    "source": "manual",
    "notes": "Angels House - Nicomar"
  },
  {
    "url": "https://www.memoraeterna.ro/",
    "source": "manual", 
    "notes": "Memora Eterna - multiple locations"
  },
  {
    "url": "https://angelshousefuneral.ro/",
    "source": "manual",
    "notes": "Angels House Funeral"
  },
  {
    "url": "https://funeraretimisoara.ro/",
    "source": "manual",
    "notes": "Subin Funerare"
  },
  {
    "url": "https://serviciifunerare-timisoara.ro/",
    "source": "manual",
    "notes": "Servicii Funerare SRL"
  },
  {
    "url": "https://funerarotim.ro/",
    "source": "manual",
    "notes": "Pompe Funebre Timisoara"
  },
  {
    "url": "https://memorialfunerare.ro/",
    "source": "manual",
    "notes": "Memorial Funerare"
  },
  {
    "url": "https://www.casafunerara.ro/",
    "source": "manual",
    "notes": "Casa Funerara"
  },
  {
    "url": "https://servicii-funerare.ro/",
    "source": "manual",
    "notes": "Servicii Funerare"
  },
  {
    "url": "https://funerar.ro/",
    "source": "manual",
    "notes": "Funerar.ro"
  },
  {
    "url": "https://casafunerararitm.ro/",
    "source": "manual",
    "notes": "Casa Funerara Ritm"
  },
  {
    "url": "https://funerariasol.ro/",
    "source": "manual",
    "notes": "Funeraria Sol"
  },
  {
    "url": "https://funeraretimis.ro/",
    "source": "manual",
    "notes": "Funerare Timis"
  },
  {
    "url": "https://casafunerara-paradis.ro/",
    "source": "manual",
    "notes": "Casa Funerara Paradis"
  },
  {
    "url": "https://funeraretimisoara.com/",
    "source": "manual",
    "notes": "Funerare Timisoara"
  }
]
